Metadata-Version: 1.0
Name: datascitools
Version: 0.0.1
Summary: Tools for data science
Home-page: UNKNOWN
Author: Jason Xing Zhang
Author-email: jason.xing.zhang@gmail.com
License: MIT License
Platform: any
